README.md
setup.py
ascend_io_dbt_utils.egg-info/PKG-INFO
ascend_io_dbt_utils.egg-info/SOURCES.txt
ascend_io_dbt_utils.egg-info/dependency_links.txt
ascend_io_dbt_utils.egg-info/entry_points.txt
ascend_io_dbt_utils.egg-info/requires.txt
ascend_io_dbt_utils.egg-info/top_level.txt
packages/__init__.py
packages/cli.py
packages/component_module.py
packages/manifest_utils.py
packages/process_module.py
packages/run_tests_module.py
packages/transform_utils.py
tests/test_get_tests_and_nodes.py
tests/test_parse_manifest.py
tests/test_topological_sort.py
tests/test_translate_sql.py