Metadata-Version: 2.1
Name: ascend-io-dbt-utils
Version: 0.11.1
Summary: Utilities for dbt and Ascend
Home-page: https://github.com/michaelhyatt/ascend_dbt_transform
